qiskit_debugger.py
qiskit_debugger-0.1.2.dist-info/LICENSE
qiskit_debugger-0.1.2.dist-info/METADATA
qiskit_debugger-0.1.2.dist-info/WHEEL
qiskit_debugger-0.1.2.dist-info/top_level.txt
qiskit_debugger-0.1.2.dist-info/RECORD
