Metadata-Version: 2.1
Name: qiskit-debugger
Version: 0.1.2
Summary: Quantum Circuit debugger for the Qiskit SDK.
Author-email: Sirajus Salekin <ssalekin14@gmail.com>, Palvit Garg <pgarg5@ncsu.edu>, Harshwardhan Joshi <hjoshi2@ncsu.edu>
Maintainer-email: Sirajus Salekin <ssalekin14@gmail.com>
License: MIT License
Project-URL: homepage, https://github.com/salekinsirajus/quantum_circuit_debugger
Project-URL: repository, https://github.com/salekinsirajus/quantum_circuit_debugger
Keywords: quantum,computing,debugger,qiskit
Classifier: License :: OSI Approved :: MIT License
Classifier: Programming Language :: Python :: 3
Classifier: Programming Language :: Python :: 3.11
Classifier: Operating System :: OS Independent
Classifier: Development Status :: 3 - Alpha
Requires-Python: >=3.6
License-File: LICENSE
Requires-Dist: qiskit (==0.43.2)
